{
    "model_type": "import torch.nn as nn\nimport torch.nn.functional as F\n\n# class ResBlock(nn.Module):\n#     def __init__(self,device) -> None:\n#         super().__init__()\n        \n#     def forward(self,x):\n#         return nn.ReLU(self.net(x)+x)\n# class BigResBlock(nn.Module):\n#     def __init__(self) -> None:\n#         super().__init__()\n#         self.net = [ResBlock(),ResBlock(),ResBlock()]\n#     def forward(self,x):\n#         for lyer in self.net:\n#             x=lyer(x)\n#         return x\nclass Net(nn.Module):\n    def createManyResBlock(self,channels=64,BlockNum=3,kernel_size=3):\n        self.cnt+=1\n        manyResBlock = []\n        for i in range(BlockNum):\n            x = nn.Sequential(\n                nn.Conv2d(channels,channels,kernel_size,padding=(kernel_size-1)//2),\n                nn.BatchNorm2d(channels),\n                nn.ReLU(),\n                # nn.Dropout2d(0.1),\n                nn.Conv2d(channels,channels,kernel_size,padding=(kernel_size-1)//2),\n            )\n            self.add_module(f'{self.cnt}_{i}',x)\n            manyResBlock.append(x)\n        return manyResBlock\n    def PassThrough(self,manyResBlock:list,x):\n        for i in range(len(manyResBlock)):\n            x = F.relu(x+manyResBlock[i](x))\n            # if i%2:\n            #     x = nn.MaxPool2d(2)(x)\n        return x\n\n    def __init__(self):\n        super(\n#&&&&&&&&&&&&&&&&&&&&&&&&&&&&&&&&&&&&&&&\n            Net,self\n#&&&&&&&&&&&&&&&&&&&&&&&&&&&&&&&&&&&&&&&\n        ).__init__()\n        self.cnt=0\n        \n        self.conv1 = nn.Sequential(\n            nn.Conv2d(3,64,7,stride=2,padding=3),\n            nn.BatchNorm2d(64),\n            nn.MaxPool2d(2),\n            # nn.Dropout2d(0.35)\n        )\n        self.manyResBlock1 = self.createManyResBlock()\n        self.conv2 =  nn.Sequential(\n            nn.Conv2d(64,128,3,stride=2,padding=1),\n            nn.BatchNorm2d(128),\n            nn.MaxPool2d(2),\n            # nn.Dropout2d(0.35)\n        )\n        self.manyResBlock2 = self.createManyResBlock(channels=128\n                                                    #  ,BlockNum=4\n                                                     )\n        self.conv3 = nn.Sequential(\n            nn.Conv2d(128,192,3,padding=1),\n            nn.BatchNorm2d(192),\n            nn.MaxPool2d(2),\n            # nn.Dropout2d(0.35)\n            )\n        self.manyResBlock3 = self.createManyResBlock(channels=192\n                                                    #  ,BlockNum=5\n                                                     )\n        self.final = nn.Sequential(\n            nn.Linear(192,256),\n            # nn.Dropout1d(0.2),\n            nn.ReLU(),\n            nn.Linear(256,64),\n            # nn.Dropout1d(0.2),\n            nn.ReLU(),\n            nn.Linear(64,10),\n        )\n    def forward(self, x):\n        bsize = x.shape[0]\n        x = self.pre_process(x)\n        x = self.conv1(x)\n        # print('after conv1',x.shape)\n        x = self.PassThrough(self.manyResBlock1,x)\n        # print('after block 1',x.shape)\n        x = self.conv2(x)\n        # print('after conv2',x.shape)\n        x = self.PassThrough(self.manyResBlock2,x)\n        # print('after block 2',x.shape)\n        x = self.conv3(x)\n        # print('after conv3',x.shape)\n        x = self.PassThrough(self.manyResBlock3,x)\n        # print('after block 3',x.shape)\n        x = nn.AvgPool2d(4)(x)\n        y = x.reshape(bsize,-1)\n        x = self.final(y)\n        return x\n    def to(self,device):\n        self.final.to(device)\n        lst1 = [\n            self.conv1,\n                self.conv2,\n                self.conv3\n                ]\n        for i in lst1:\n            i.to(device)\n        lst = [\n            self.manyResBlock1,\n            self.manyResBlock2,\n            self.manyResBlock3\n            ]\n        for i in lst:\n            for j in i:\n                j.to(device)\n    def pre_process(self, x):\n        return x.float()",
    "train_history": [
        {
            "optimizer": {
                "lr": 0.0005,
                "betas": [
                    0.9,
                    0.999
                ],
                "eps": 1e-08,
                "weight_decay": 4e-05,
                "amsgrad": false,
                "maximize": false,
                "foreach": null,
                "capturable": false,
                "differentiable": false,
                "fused": null
            },
            "epochs": 10,
            "results": [
                {
                    "train accuracy": 32.9,
                    "valid accuracy": 40.85,
                    "loss": 0.22045749425888062,
                    "valid loss": 0.049161672592163086
                },
                {
                    "train accuracy": 48.2575,
                    "valid accuracy": 55.78,
                    "loss": 0.1765119880437851,
                    "valid loss": 0.03845658153295517
                },
                {
                    "train accuracy": 56.915,
                    "valid accuracy": 63.91,
                    "loss": 0.1496347337961197,
                    "valid loss": 0.030573418363928795
                },
                {
                    "train accuracy": 62.8225,
                    "valid accuracy": 68.79,
                    "loss": 0.1299779713153839,
                    "valid loss": 0.027503328397870064
                },
                {
                    "train accuracy": 67.1325,
                    "valid accuracy": 71.72,
                    "loss": 0.1159062460064888,
                    "valid loss": 0.025261780247092247
                },
                {
                    "train accuracy": 70.6475,
                    "valid accuracy": 76.54,
                    "loss": 0.10525214672088623,
                    "valid loss": 0.020880574360489845
                },
                {
                    "train accuracy": 73.4575,
                    "valid accuracy": 78.2,
                    "loss": 0.09595426917076111,
                    "valid loss": 0.019874053075909615
                },
                {
                    "train accuracy": 75.465,
                    "valid accuracy": 79.96,
                    "loss": 0.08903824537992477,
                    "valid loss": 0.018181966617703438
                },
                {
                    "train accuracy": 76.9,
                    "valid accuracy": 79.97,
                    "loss": 0.08380620181560516,
                    "valid loss": 0.018185263499617577
                },
                {
                    "train accuracy": 78.2175,
                    "valid accuracy": 81.32,
                    "loss": 0.07872547954320908,
                    "valid loss": 0.016868259757757187
                }
            ]
        },
        {
            "optimizer": {
                "lr": 0.00045,
                "betas": [
                    0.9,
                    0.999
                ],
                "eps": 1e-08,
                "weight_decay": 4e-05,
                "amsgrad": false,
                "maximize": false,
                "foreach": null,
                "capturable": false,
                "differentiable": false,
                "fused": null
            },
            "epochs": 10,
            "results": [
                {
                    "train accuracy": 79.7,
                    "valid accuracy": 82.14,
                    "loss": 0.07354388386011124,
                    "valid loss": 0.01662334054708481
                },
                {
                    "train accuracy": 80.985,
                    "valid accuracy": 83.3,
                    "loss": 0.0692470520734787,
                    "valid loss": 0.015464195050299168
                },
                {
                    "train accuracy": 81.6875,
                    "valid accuracy": 84.52,
                    "loss": 0.06651753932237625,
                    "valid loss": 0.014406402595341206
                },
                {
                    "train accuracy": 82.5775,
                    "valid accuracy": 85.03,
                    "loss": 0.06331061571836472,
                    "valid loss": 0.013882218860089779
                },
                {
                    "train accuracy": 83.35,
                    "valid accuracy": 85.07,
                    "loss": 0.06076952815055847,
                    "valid loss": 0.01392015814781189
                },
                {
                    "train accuracy": 83.8575,
                    "valid accuracy": 86.11,
                    "loss": 0.058821000158786774,
                    "valid loss": 0.012899339199066162
                },
                {
                    "train accuracy": 84.3775,
                    "valid accuracy": 86.02,
                    "loss": 0.05655207857489586,
                    "valid loss": 0.012976604513823986
                },
                {
                    "train accuracy": 84.735,
                    "valid accuracy": 86.47,
                    "loss": 0.05513212829828262,
                    "valid loss": 0.012419435195624828
                },
                {
                    "train accuracy": 85.43,
                    "valid accuracy": 86.7,
                    "loss": 0.052920397371053696,
                    "valid loss": 0.012419583275914192
                },
                {
                    "train accuracy": 85.6525,
                    "valid accuracy": 86.75,
                    "loss": 0.05189235135912895,
                    "valid loss": 0.01223031710833311
                }
            ]
        },
        {
            "optimizer": {
                "lr": 0.0006,
                "betas": [
                    0.9,
                    0.999
                ],
                "eps": 1e-08,
                "weight_decay": 3e-05,
                "amsgrad": false,
                "maximize": false,
                "foreach": null,
                "capturable": false,
                "differentiable": false,
                "fused": null
            },
            "epochs": 10,
            "results": [
                {
                    "train accuracy": 84.945,
                    "valid accuracy": 86.16,
                    "loss": 0.05520961806178093,
                    "valid loss": 0.013121102936565876
                },
                {
                    "train accuracy": 85.4125,
                    "valid accuracy": 86.59,
                    "loss": 0.05341756343841553,
                    "valid loss": 0.012447183951735497
                },
                {
                    "train accuracy": 85.925,
                    "valid accuracy": 86.55,
                    "loss": 0.05150860920548439,
                    "valid loss": 0.012554256245493889
                },
                {
                    "train accuracy": 86.3325,
                    "valid accuracy": 86.18,
                    "loss": 0.049922097474336624,
                    "valid loss": 0.013160288333892822
                },
                {
                    "train accuracy": 86.2525,
                    "valid accuracy": 85.47,
                    "loss": 0.049810465425252914,
                    "valid loss": 0.013846047222614288
                },
                {
                    "train accuracy": 86.8775,
                    "valid accuracy": 86.84,
                    "loss": 0.047895848751068115,
                    "valid loss": 0.012827103957533836
                },
                {
                    "train accuracy": 87.18,
                    "valid accuracy": 87.4,
                    "loss": 0.046469878405332565,
                    "valid loss": 0.012206216342747211
                },
                {
                    "train accuracy": 87.5075,
                    "valid accuracy": 87.27,
                    "loss": 0.04528512433171272,
                    "valid loss": 0.012162482365965843
                },
                {
                    "train accuracy": 87.965,
                    "valid accuracy": 87.88,
                    "loss": 0.04434400051832199,
                    "valid loss": 0.011437660083174706
                },
                {
                    "train accuracy": 88.24,
                    "valid accuracy": 86.67,
                    "loss": 0.04280034825205803,
                    "valid loss": 0.013283648528158665
                }
            ]
        },
        {
            "optimizer": {
                "lr": 0.0007,
                "betas": [
                    0.9,
                    0.999
                ],
                "eps": 1e-08,
                "weight_decay": 3e-05,
                "amsgrad": false,
                "maximize": false,
                "foreach": null,
                "capturable": false,
                "differentiable": false,
                "fused": null
            },
            "epochs": 10,
            "results": [
                {
                    "train accuracy": 87.6475,
                    "valid accuracy": 88.49,
                    "loss": 0.044947683811187744,
                    "valid loss": 0.01118936762213707
                },
                {
                    "train accuracy": 88.02,
                    "valid accuracy": 87.67,
                    "loss": 0.04395677521824837,
                    "valid loss": 0.012010348960757256
                },
                {
                    "train accuracy": 88.1025,
                    "valid accuracy": 88.36,
                    "loss": 0.04321913793683052,
                    "valid loss": 0.011051196604967117
                },
                {
                    "train accuracy": 88.3625,
                    "valid accuracy": 87.67,
                    "loss": 0.042022839188575745,
                    "valid loss": 0.011579182930290699
                },
                {
                    "train accuracy": 88.5825,
                    "valid accuracy": 88.48,
                    "loss": 0.04153270274400711,
                    "valid loss": 0.010861968621611595
                },
                {
                    "train accuracy": 88.9175,
                    "valid accuracy": 89.04,
                    "loss": 0.04042566940188408,
                    "valid loss": 0.010756702162325382
                },
                {
                    "train accuracy": 89.17,
                    "valid accuracy": 87.83,
                    "loss": 0.03934941440820694,
                    "valid loss": 0.011439340189099312
                },
                {
                    "train accuracy": 89.6275,
                    "valid accuracy": 88.46,
                    "loss": 0.0384625680744648,
                    "valid loss": 0.011037127114832401
                },
                {
                    "train accuracy": 89.51,
                    "valid accuracy": 89.36,
                    "loss": 0.03815576061606407,
                    "valid loss": 0.010271774604916573
                },
                {
                    "train accuracy": 89.64,
                    "valid accuracy": 89.26,
                    "loss": 0.0369255505502224,
                    "valid loss": 0.010639311745762825
                }
            ]
        },
        {
            "optimizer": {
                "lr": 0.0006,
                "betas": [
                    0.9,
                    0.999
                ],
                "eps": 1e-08,
                "weight_decay": 4e-05,
                "amsgrad": false,
                "maximize": false,
                "foreach": null,
                "capturable": false,
                "differentiable": false,
                "fused": null
            },
            "epochs": 10,
            "results": [
                {
                    "train accuracy": 90.5525,
                    "valid accuracy": 88.28,
                    "loss": 0.034425538033246994,
                    "valid loss": 0.011557619087398052
                },
                {
                    "train accuracy": 90.71,
                    "valid accuracy": 88.58,
                    "loss": 0.03376463055610657,
                    "valid loss": 0.01111783180385828
                },
                {
                    "train accuracy": 90.925,
                    "valid accuracy": 89.95,
                    "loss": 0.03285502642393112,
                    "valid loss": 0.009956161491572857
                },
                {
                    "train accuracy": 91.18,
                    "valid accuracy": 89.0,
                    "loss": 0.0321795828640461,
                    "valid loss": 0.01097969152033329
                },
                {
                    "train accuracy": 91.2425,
                    "valid accuracy": 89.27,
                    "loss": 0.0319027304649353,
                    "valid loss": 0.010744255967438221
                },
                {
                    "train accuracy": 91.2875,
                    "valid accuracy": 89.47,
                    "loss": 0.03176054731011391,
                    "valid loss": 0.010843431577086449
                },
                {
                    "train accuracy": 91.5175,
                    "valid accuracy": 89.61,
                    "loss": 0.030603667721152306,
                    "valid loss": 0.010162289254367352
                },
                {
                    "train accuracy": 91.4475,
                    "valid accuracy": 89.94,
                    "loss": 0.030765941366553307,
                    "valid loss": 0.00997435487806797
                },
                {
                    "train accuracy": 91.5725,
                    "valid accuracy": 89.14,
                    "loss": 0.030606282874941826,
                    "valid loss": 0.010674173012375832
                },
                {
                    "train accuracy": 91.7725,
                    "valid accuracy": 89.68,
                    "loss": 0.029873603954911232,
                    "valid loss": 0.00969773717224598
                }
            ]
        },
        {
            "optimizer": {
                "lr": 0.0006,
                "betas": [
                    0.9,
                    0.999
                ],
                "eps": 1e-08,
                "weight_decay": 4e-05,
                "amsgrad": false,
                "maximize": false,
                "foreach": null,
                "capturable": false,
                "differentiable": false,
                "fused": null
            },
            "epochs": 10,
            "results": [
                {
                    "train accuracy": 91.9425,
                    "valid accuracy": 89.5,
                    "loss": 0.0293876975774765,
                    "valid loss": 0.010348024778068066
                },
                {
                    "train accuracy": 91.9425,
                    "valid accuracy": 89.91,
                    "loss": 0.028756752610206604,
                    "valid loss": 0.010040667839348316
                },
                {
                    "train accuracy": 92.015,
                    "valid accuracy": 89.67,
                    "loss": 0.0292048417031765,
                    "valid loss": 0.01019657775759697
                },
                {
                    "train accuracy": 92.2925,
                    "valid accuracy": 89.96,
                    "loss": 0.02840467542409897,
                    "valid loss": 0.010495869442820549
                },
                {
                    "train accuracy": 92.2025,
                    "valid accuracy": 90.42,
                    "loss": 0.028368374332785606,
                    "valid loss": 0.009574182331562042
                },
                {
                    "train accuracy": 92.2675,
                    "valid accuracy": 89.05,
                    "loss": 0.02755916677415371,
                    "valid loss": 0.010865166783332825
                },
                {
                    "train accuracy": 92.3225,
                    "valid accuracy": 89.96,
                    "loss": 0.027619261294603348,
                    "valid loss": 0.009954709559679031
                },
                {
                    "train accuracy": 92.4625,
                    "valid accuracy": 89.75,
                    "loss": 0.02728653885424137,
                    "valid loss": 0.010201072320342064
                },
                {
                    "train accuracy": 92.335,
                    "valid accuracy": 89.42,
                    "loss": 0.027542565017938614,
                    "valid loss": 0.009973987936973572
                },
                {
                    "train accuracy": 92.6875,
                    "valid accuracy": 89.84,
                    "loss": 0.026620663702487946,
                    "valid loss": 0.009706881828606129
                }
            ]
        },
        {
            "optimizer": {
                "lr": 0.0005,
                "betas": [
                    0.9,
                    0.999
                ],
                "eps": 1e-08,
                "weight_decay": 8e-05,
                "amsgrad": false,
                "maximize": false,
                "foreach": null,
                "capturable": false,
                "differentiable": false,
                "fused": null
            },
            "epochs": 10,
            "results": [
                {
                    "train accuracy": 93.15,
                    "valid accuracy": 90.3,
                    "loss": 0.024867793545126915,
                    "valid loss": 0.009985639713704586
                },
                {
                    "train accuracy": 93.3675,
                    "valid accuracy": 89.95,
                    "loss": 0.024104712530970573,
                    "valid loss": 0.010304060764610767
                },
                {
                    "train accuracy": 93.245,
                    "valid accuracy": 90.46,
                    "loss": 0.024248018860816956,
                    "valid loss": 0.009958119131624699
                },
                {
                    "train accuracy": 93.1775,
                    "valid accuracy": 89.78,
                    "loss": 0.024735519662499428,
                    "valid loss": 0.010498803108930588
                },
                {
                    "train accuracy": 93.385,
                    "valid accuracy": 89.85,
                    "loss": 0.02412535436451435,
                    "valid loss": 0.010008406825363636
                },
                {
                    "train accuracy": 93.385,
                    "valid accuracy": 90.29,
                    "loss": 0.024299047887325287,
                    "valid loss": 0.010356174781918526
                },
                {
                    "train accuracy": 93.315,
                    "valid accuracy": 90.36,
                    "loss": 0.024227764457464218,
                    "valid loss": 0.010031921789050102
                },
                {
                    "train accuracy": 93.4325,
                    "valid accuracy": 90.19,
                    "loss": 0.024218184873461723,
                    "valid loss": 0.009900365024805069
                },
                {
                    "train accuracy": 93.195,
                    "valid accuracy": 90.61,
                    "loss": 0.024599358439445496,
                    "valid loss": 0.009587188251316547
                },
                {
                    "train accuracy": 93.33,
                    "valid accuracy": 90.16,
                    "loss": 0.02421814575791359,
                    "valid loss": 0.010504638776183128
                }
            ]
        }
    ],
    "description": "\n        ???        \n        ",
    "test_acc": 87.78999999999999
}